sigdetect/__init__.py
sigdetect/api.py
sigdetect/cli.py
sigdetect/config.py
sigdetect/cropping.py
sigdetect/eda.py
sigdetect/logging_setup.py
sigdetect/utils.py
sigdetect/wet_detection.py
sigdetect/data/role_rules.retainer.yml
sigdetect/data/role_rules.yml
sigdetect/data/vendor_patterns.yml
sigdetect/detector/__init__.py
sigdetect/detector/base.py
sigdetect/detector/base_detector.py
sigdetect/detector/file_result_model.py
sigdetect/detector/pymupdf_engine.py
sigdetect/detector/pypdf2_engine.py
sigdetect/detector/signature_model.py
sigdetect-0.5.2.dist-info/METADATA
sigdetect-0.5.2.dist-info/WHEEL
sigdetect-0.5.2.dist-info/entry_points.txt
sigdetect-0.5.2.dist-info/top_level.txt
sigdetect-0.5.2.dist-info/RECORD
