Metadata-Version: 2.4
Name: sigdetect
Version: 0.5.2
Summary: Signature detection and role attribution for PDFs
Author-email: BT Asmamaw <basmamaw@angeiongroup.com>
License: MIT
Requires-Python: >=3.9
Requires-Dist: pypdf>=4.0.0
Requires-Dist: rich>=13.0
Requires-Dist: typer>=0.12
Requires-Dist: pydantic>=2.5
Requires-Dist: pillow>=10.0
Requires-Dist: python-docx>=1.1.0
Requires-Dist: pytesseract>=0.3.10
Requires-Dist: pymupdf>=1.23
Requires-Dist: pyyaml>=6.0
